{
  "aggregate": {
    "timestamp": "2020-10-29T09:46:55.946Z",
    "scenariosCreated": 3000,
    "scenariosCompleted": 3000,
    "requestsCompleted": 4454,
    "latency": {
      "min": 0.6,
      "max": 61.5,
      "median": 2.2,
      "p95": 5.3,
      "p99": 12.2
    },
    "rps": {
      "count": 4454,
      "mean": 146.08
    },
    "scenarioDuration": {
      "min": 3.5,
      "max": 105.8,
      "median": 6.8,
      "p95": 13.8,
      "p99": 22.8
    },
    "scenarioCounts": {
      "Get Rides": 1546,
      "Insert Rides": 1454
    },
    "errors": {},
    "codes": {
      "200": 4454
    },
    "matches": 0,
    "customStats": {},
    "counters": {},
    "scenariosAvoided": 0,
    "phases": [
      {
        "duration": 30,
        "arrivalRate": 100,
        "name": "Sustained load"
      }
    ]
  },
  "intermediate": [
    {
      "timestamp": "2020-10-29T09:46:35.408Z",
      "scenariosCreated": 999,
      "scenariosCompleted": 998,
      "requestsCompleted": 1474,
      "latency": {
        "min": 0.7,
        "max": 61.5,
        "median": 2.5,
        "p95": 6.7,
        "p99": 18
      },
      "rps": {
        "count": 1475,
        "mean": 148.24
      },
      "scenarioDuration": {
        "min": 3.6,
        "max": 105.8,
        "median": 7.7,
        "p95": 16.8,
        "p99": 43.4
      },
      "scenarioCounts": {
        "Get Rides": 522,
        "Insert Rides": 477
      },
      "errors": {},
      "codes": {
        "200": 1474
      },
      "matches": 0,
      "latencies": [
        54764495,
        51539015,
        40562697,
        44329161,
        42910042,
        54569924,
        61479204,
        54891875,
        28061845,
        16835359,
        48985446,
        40939868,
        11061829,
        4267617,
        4356531,
        4460542,
        18239254,
        7351299,
        17093308,
        17080064,
        7008700,
        2268199,
        2749198,
        4431171,
        2350881,
        8567463,
        1609581,
        5858909,
        2458105,
        7468102,
        1820643,
        6099970,
        1876408,
        3401819,
        3397678,
        5181731,
        2039736,
        2623854,
        2643763,
        3066134,
        9512101,
        2133985,
        3515607,
        5843521,
        1637560,
        2993430,
        3086651,
        3434148,
        5509813,
        1727334,
        5938352,
        1605031,
        7221920,
        2177568,
        6962335,
        1605390,
        2589520,
        2391060,
        3159409,
        4702667,
        1067738,
        2543949,
        3064359,
        4974398,
        1702979,
        5011444,
        2043620,
        5148104,
        1985474,
        2731593,
        4879022,
        2027193,
        2639646,
        2899778,
        4914269,
        1986010,
        4655010,
        2480151,
        2522435,
        2619182,
        4235266,
        7124685,
        1918500,
        3103559,
        3438563,
        5504970,
        3248228,
        3282991,
        3470209,
        4864741,
        1051609,
        2426809,
        6416007,
        1302180,
        2429200,
        4758531,
        2728796,
        5251155,
        1466589,
        4447313,
        1168832,
        2261343,
        5602516,
        1249453,
        2232077,
        2530445,
        13772766,
        8488708,
        13345501,
        7027498,
        1912569,
        3425849,
        3046761,
        3641424,
        2580985,
        4101785,
        5620764,
        1386095,
        2540495,
        5470363,
        1532587,
        2670577,
        2446549,
        4006614,
        15866158,
        1143007,
        2456247,
        4685837,
        1400979,
        2755535,
        8681041,
        1547000,
        8583671,
        4306733,
        10341417,
        8655566,
        2935130,
        7873408,
        2429170,
        3010935,
        2338807,
        2327795,
        5684180,
        1765217,
        4672380,
        1501145,
        2461135,
        5528515,
        1669152,
        5407252,
        1252401,
        2614282,
        5093463,
        1633005,
        8331068,
        1133344,
        3544557,
        2819580,
        8011018,
        1566574,
        4831053,
        1460883,
        4542422,
        1896785,
        2761812,
        5087697,
        1366795,
        3310496,
        5761058,
        1631210,
        8180367,
        1598542,
        2501996,
        2320700,
        5508976,
        1593574,
        2309409,
        2532580,
        5233510,
        1977103,
        5208401,
        1469000,
        2490576,
        2712570,
        5248076,
        1525826,
        5094125,
        2106183,
        6479138,
        1847580,
        3403122,
        2798438,
        4200064,
        1732419,
        2685532,
        4801304,
        1009618,
        2423225,
        2757471,
        3275597,
        2426860,
        3077058,
        2845675,
        6871390,
        2565681,
        6245573,
        1640628,
        6092100,
        1685363,
        4870627,
        1257756,
        2594716,
        2364961,
        2724134,
        4570555,
        993667,
        4543892,
        1074222,
        5347419,
        1481347,
        4639982,
        1440148,
        5673468,
        2266155,
        2983695,
        2884547,
        9559053,
        1619455,
        3531054,
        3147307,
        4131996,
        1015328,
        2217077,
        3164356,
        4069828,
        1023296,
        2371387,
        4946911,
        2298680,
        4531639,
        952040,
        2306587,
        2352813,
        2618784,
        2243588,
        6217120,
        2157511,
        8966000,
        6431950,
        3013207,
        1602542,
        2177729,
        2347197,
        2623109,
        2784580,
        2374761,
        3648431,
        2505063,
        2365675,
        3532610,
        2769496,
        2631406,
        4776359,
        2459845,
        4695558,
        2253411,
        2659173,
        2649495,
        12104844,
        6185083,
        1356171,
        2382352,
        4784103,
        1901153,
        2914653,
        2490440,
        2863705,
        2527151,
        2190002,
        4326189,
        1675454,
        4863973,
        1105215,
        2143405,
        2178533,
        5138225,
        2301823,
        3971402,
        986367,
        2510974,
        4828697,
        2078110,
        2338075,
        2214829,
        2578446,
        6711941,
        3364627,
        5231867,
        1342325,
        8211428,
        3178151,
        6669042,
        1201219,
        2152676,
        4612857,
        1065343,
        6229303,
        1751061,
        2999139,
        2350888,
        2347177,
        6882182,
        1337692,
        4152104,
        1928935,
        2465148,
        2532225,
        2378975,
        2342028,
        5008801,
        2586227,
        4545245,
        1870869,
        2303483,
        4006357,
        1832990,
        4473390,
        2245330,
        4436989,
        4304731,
        4963167,
        1918656,
        3013674,
        4150332,
        909790,
        2341940,
        4248873,
        873537,
        4127771,
        902766,
        3806387,
        1379923,
        2834972,
        2701024,
        2412187,
        2362241,
        4417630,
        1423332,
        4802605,
        2107559,
        6663948,
        1214445,
        2269913,
        4196354,
        877917,
        2217663,
        2906119,
        9427917,
        9266526,
        3980665,
        1403339,
        5077500,
        1096834,
        3819365,
        1612427,
        2140504,
        4521272,
        1343408,
        4330392,
        967098,
        2152712,
        2179802,
        2928302,
        3889665,
        857095,
        3987284,
        941997,
        4751203,
        2067750,
        3891871,
        1686957,
        4122676,
        1374151,
        4299064,
        1166798,
        2405729,
        4765237,
        1561083,
        3742835,
        2891690,
        2922016,
        4106998,
        1073077,
        3925393,
        976076,
        5938099,
        1793275,
        2247054,
        2803123,
        2778727,
        6222771,
        1451092,
        3730336,
        891575,
        6066176,
        1689343,
        3122747,
        3322301,
        4289882,
        1880239,
        3392494,
        2919725,
        4406912,
        1556130,
        2711640,
        2542123,
        2242682,
        4040661,
        1532743,
        4450608,
        1072428,
        13997825,
        5310770,
        2484396,
        3692075,
        884159,
        3608701,
        873381,
        4687410,
        2635355,
        4226214,
        923461,
        2208082,
        2186715,
        2342034,
        3966952,
        1520870,
        4040466,
        915734,
        4777460,
        2196825,
        3906272,
        952851,
        3742223,
        871973,
        2467498,
        4106442,
        863148,
        3709873,
        1023468,
        3990201,
        1147111,
        2869052,
        2280878,
        2244650,
        3208194,
        2215148,
        5194757,
        1032987,
        2973048,
        2404692,
        3970924,
        1393904,
        2189716,
        3919112,
        901312,
        3492841,
        872848,
        2084622,
        3132527,
        2270826,
        2535965,
        2249879,
        4368399,
        1072259,
        2822150,
        4004590,
        1252595,
        4420765,
        1051157,
        2231647,
        7127798,
        2286142,
        5101968,
        1614277,
        2267123,
        2188614,
        2893422,
        2439412,
        3840286,
        903530,
        4019574,
        1683177,
        2925036,
        3711707,
        916987,
        3686162,
        900224,
        4950876,
        2164752,
        2472120,
        3714070,
        823194,
        2176060,
        2638112,
        3820450,
        989768,
        3757919,
        934031,
        2683992,
        2185753,
        6031499,
        1772047,
        4921123,
        3251948,
        9918316,
        8769027,
        5790660,
        9663677,
        1473013,
        4361465,
        1149660,
        3810986,
        884922,
        4210963,
        1009958,
        2326059,
        2714290,
        3782031,
        1003425,
        4566972,
        2655096,
        3762273,
        928045,
        3724938,
        919596,
        6073893,
        1499998,
        4256793,
        1050637,
        2278143,
        2209670,
        3383064,
        2398155,
        2088994,
        4516132,
        2465963,
        2153643,
        2175574,
        2352602,
        2384454,
        5413949,
        1919956,
        4436951,
        4155175,
        1078507,
        2109764,
        2477185,
        5169225,
        1305441,
        3718494,
        1176656,
        4668423,
        2333801,
        3968407,
        1389821,
        2915057,
        2224884,
        2366050,
        2750272,
        3646430,
        932649,
        3597358,
        14139692,
        9886328,
        2175406,
        3941013,
        882407,
        2924673,
        4943922,
        863110,
        2178870,
        2193579,
        3870682,
        929579,
        2063102,
        3560583,
        1105409,
        4710528,
        2689602,
        3643905,
        908028,
        2240555,
        2852805,
        2344749,
        2207702,
        4248890,
        1724909,
        2689959,
        4277218,
        914784,
        2476387,
        3151697,
        3202735,
        3560200,
        1042374,
        2920062,
        3918439,
        917697,
        3916671,
        925744,
        3526351,
        1010591,
        3636283,
        1012322,
        2444474,
        3855821,
        854546,
        2500786,
        3687777,
        889288,
        3662042,
        821577,
        2379004,
        4864613,
        1026473,
        3754815,
        976675,
        2297054,
        3909299,
        1170151,
        3367940,
        1197188,
        2236401,
        6228597,
        1247734,
        3355527,
        852972,
        3358778,
        851968,
        4169466,
        1481822,
        2112140,
        3412347,
        975134,
        2202578,
        2543823,
        2174349,
        2090441,
        3650673,
        1032593,
        3722903,
        2023444,
        2989198,
        4453607,
        1494984,
        2380707,
        3709595,
        931687,
        2154575,
        2768035,
        2172570,
        1677511,
        4018729,
        1142725,
        2098654,
        2155073,
        2724273,
        4036302,
        877340,
        3569147,
        939116,
        2215534,
        2741033,
        2527668,
        2075409,
        4792641,
        1565559,
        3320732,
        900744,
        3583445,
        1881288,
        5050215,
        1183318,
        2715688,
        2162813,
        2491850,
        4069864,
        1181687,
        2017281,
        2127327,
        2553494,
        2274676,
        2189709,
        4348279,
        1409535,
        4000834,
        1170862,
        5377910,
        6587658,
        1394391,
        3489688,
        948625,
        2388561,
        5097844,
        2863296,
        5411014,
        1325305,
        5048642,
        2741173,
        3029771,
        2568586,
        3750745,
        1107204,
        3643232,
        1856682,
        4115966,
        2023293,
        3438305,
        884893,
        2190614,
        2412570,
        13354826,
        2650659,
        820163,
        5511791,
        2115536,
        2355943,
        3651225,
        857755,
        2200420,
        4993748,
        4895751,
        2177063,
        1905981,
        4661656,
        2350546,
        2254658,
        3539647,
        876916,
        2148467,
        2329283,
        2473019,
        2401277,
        2662780,
        3671070,
        972907,
        2244713,
        3321748,
        3390055,
        877440,
        2287628,
        4567255,
        2503721,
        4061207,
        1002552,
        2219476,
        5964142,
        4208214,
        8133543,
        2286497,
        9623610,
        2110558,
        12443121,
        1637755,
        5641995,
        4415128,
        1367008,
        2128473,
        2841583,
        3823102,
        837296,
        2329419,
        2224445,
        5463373,
        1629115,
        2239910,
        4582353,
        3563845,
        2690648,
        2271580,
        2127430,
        4039824,
        1446034,
        2509019,
        3701688,
        871171,
        2530178,
        3989203,
        1187795,
        2018710,
        3469377,
        852789,
        2219241,
        2290141,
        3094897,
        4650844,
        1452181,
        2741433,
        3809223,
        986448,
        3698209,
        1143890,
        2444922,
        2196341,
        3631932,
        893476,
        2824948,
        4527309,
        939692,
        3729520,
        853259,
        5179299,
        1850437,
        2421621,
        5580811,
        1731356,
        2503922,
        4083492,
        1496641,
        3642139,
        882799,
        2210615,
        4810783,
        2248415,
        2044878,
        2258837,
        2991452,
        2387385,
        3688424,
        1553745,
        3770876,
        1307254,
        2254280,
        2462611,
        3828693,
        844961,
        2345761,
        2278556,
        3959203,
        5354185,
        1857264,
        3757176,
        5868447,
        7053787,
        5868462,
        2061247,
        6418778,
        1289217,
        3818329,
        2557788,
        3888030,
        9179459,
        1079275,
        6212394,
        2082401,
        4130823,
        1442484,
        3921201,
        1071703,
        2494731,
        2151040,
        2244014,
        3818599,
        1697644,
        3755244,
        833310,
        2136279,
        4395261,
        1141317,
        2126334,
        19227312,
        5808674,
        4514708,
        2946250,
        2434554,
        3843236,
        1153330,
        3758678,
        994056,
        1973715,
        5002000,
        1031323,
        2352511,
        2578473,
        2855141,
        4473650,
        1492808,
        3814890,
        870387,
        2291189,
        3572986,
        1511513,
        3190711,
        2404879,
        3872470,
        1096107,
        5571107,
        1433490,
        2021362,
        3219790,
        945769,
        4190410,
        1060129,
        3786779,
        846525,
        3663565,
        881233,
        3394825,
        1015166,
        3972070,
        956374,
        2181403,
        3427957,
        862584,
        4552578,
        1216083,
        2240425,
        2300728,
        3931654,
        956402,
        2295988,
        4300360,
        1188047,
        2244736,
        2607377,
        3462470,
        919020,
        8212040,
        1480571,
        5452017,
        1032233,
        3524611,
        873517,
        2093590,
        2703079,
        3524881,
        874123,
        2181251,
        5743803,
        4433475,
        4681302,
        1096232,
        2155247,
        2117201,
        3379247,
        2172949,
        2156931,
        2805547,
        2468721,
        2127342,
        3842519,
        1160227,
        2887558,
        3398872,
        925390,
        2028570,
        4128094,
        1202330,
        3338232,
        750574,
        3439111,
        836541,
        2204500,
        4194117,
        1086940,
        3533527,
        792649,
        2214127,
        2768820,
        3456939,
        824674,
        3371957,
        966635,
        2635300,
        2242894,
        4430048,
        1087426,
        2084991,
        4028002,
        895250,
        3841622,
        1015640,
        3688382,
        957263,
        4092317,
        1099235,
        9851567,
        4254107,
        9155352,
        6708220,
        1253662,
        2402233,
        3368264,
        3196573,
        2394681,
        3857712,
        896937,
        4846374,
        4917164,
        4278407,
        1394904,
        2554876,
        3334042,
        9063877,
        4879279,
        1798468,
        4087423,
        1526688,
        3485478,
        2574247,
        4249340,
        1083792,
        2132378,
        4542800,
        1150999,
        3282323,
        1377992,
        2217059,
        2375748,
        2202047,
        2093725,
        2171877,
        15377901,
        2875114,
        6741092,
        976365,
        5251536,
        1618158,
        2738222,
        3448700,
        858428,
        3571862,
        890131,
        5606151,
        1840149,
        2296476,
        3773545,
        895746,
        2017098,
        3759438,
        837686,
        2157965,
        2120986,
        3937654,
        866970,
        2134702,
        3293611,
        806243,
        3421244,
        2279577,
        3237397,
        737147,
        2361696,
        2264896,
        4764535,
        770809,
        3526599,
        1294698,
        2900618,
        2405462,
        2073085,
        2200286,
        3726069,
        2550096,
        4656505,
        955279,
        4110839,
        1455971,
        2693159,
        3494183,
        861942,
        2427317,
        2655667,
        2184409,
        3731121,
        1109067,
        2786485,
        2228198,
        1990105,
        2308010,
        3704584,
        956210,
        2226650,
        3368920,
        975585,
        3912326,
        1041374,
        4171787,
        917383,
        2257839,
        2379260,
        2417534,
        2126188,
        3803805,
        1134145,
        3638415,
        907130,
        2095468,
        3399620,
        908706,
        2276603,
        4967585,
        1223602,
        2149515,
        2360834,
        2126659,
        3306214,
        716304,
        2572147,
        2224072,
        3417675,
        926232,
        5853052,
        1637501,
        6135568,
        4099505,
        2070190,
        3263890,
        1006223,
        4426608,
        3196404,
        2076033,
        2263625,
        2704159,
        3647653,
        1066987,
        2217340,
        2124970,
        2850466,
        2154734,
        1971063,
        2305206,
        3433364,
        786699,
        3370952,
        766949,
        4277160,
        1435952,
        4069269,
        967869,
        3339367,
        930962,
        3179818,
        2433824,
        3195945,
        1004779,
        3885024,
        4004686,
        4129521,
        4438384,
        1060161,
        2213316,
        2076501,
        3697836,
        927956,
        2238382,
        3388376,
        1354884,
        4268290,
        1329489,
        3408334,
        832284,
        2188310,
        2314102,
        2102961,
        3110371,
        726514,
        2629786,
        3396097,
        841483,
        18991323,
        12193780,
        3643304,
        808021,
        3212964,
        834585,
        4983886,
        1026631,
        2838124,
        3222558,
        763297,
        2180726,
        4105795,
        1473441,
        3515327,
        799335,
        3372498,
        904223,
        2202160,
        3449315,
        999891,
        4020650,
        1365459,
        2445970,
        3985170,
        2630808,
        4140953,
        2040759,
        3241230,
        2173820,
        2370364,
        3856058,
        823638,
        2146293,
        3490128,
        900063,
        2642710,
        2012683,
        2050297,
        4294204,
        1327168,
        3545963,
        786616,
        2345268,
        4162366,
        912128,
        3597469,
        779959,
        4590369,
        1735466,
        3657132,
        1531743,
        4024106,
        900113,
        3256920,
        825599,
        2559963,
        2671667,
        5090029,
        1546704,
        2174097,
        4237945,
        1724546,
        2249717,
        3271467,
        863017,
        3307048,
        919418,
        2279473,
        2336757,
        3965683,
        1119324,
        2706877,
        3610491,
        799830,
        3396833,
        895074,
        4032134,
        1098487,
        3673267,
        911433,
        3559141,
        899396,
        6399661,
        7807552,
        2403669,
        10003678,
        1560271,
        5141030,
        1252743,
        2301818,
        3556335,
        1391495,
        2438511,
        4665191,
        1278263,
        2543914,
        1950300,
        2898630,
        784033,
        3636170,
        867972,
        2627982,
        744326,
        2716021,
        705189,
        2919856,
        3161290,
        756344,
        4163849,
        680680,
        4190278,
        861405,
        2975221,
        855043,
        2127713,
        2212854,
        2260367,
        2724373,
        759507,
        1813579,
        2256877,
        1734155,
        3011623,
        736549,
        2501445,
        3091961,
        769068,
        3652593,
        3448262,
        1861353,
        2913523,
        3294380,
        774192,
        3613222,
        1387510,
        5457022,
        1065511,
        2101923,
        3315918,
        1053648,
        4225674,
        1689415,
        2512515,
        3781252,
        815252,
        2094481,
        4068240,
        988503,
        1977060,
        1954274,
        3824441,
        1281654,
        2116176,
        3347717,
        749230,
        2107445,
        2359407,
        5318950,
        1673755,
        2051817,
        18944907,
        1995701,
        7527913,
        3402573,
        3686431,
        2469851,
        2531110,
        4968325,
        2190819,
        8292169,
        1388426,
        2906339,
        2372465,
        3429893,
        863669,
        3299840,
        888951,
        2914563,
        3162496,
        3265196,
        875205,
        4103975,
        1023962,
        3554837,
        795039,
        2974414,
        2084199,
        3808656,
        859295,
        2091293,
        3169615,
        1133598,
        3772918,
        1690229,
        2280995,
        2259417,
        3657925,
        989692,
        3390352,
        988644,
        2413573,
        2035231,
        4210269,
        907634,
        2424333,
        3126083,
        866983,
        5909560,
        3293796,
        2350112,
        2110966,
        3333798,
        1250636,
        2467817,
        2136865,
        4195770,
        1220122,
        2415890,
        2165999,
        1923045,
        4433286,
        1264307,
        2222552,
        2184051,
        3855203,
        1093005,
        3797342,
        881348,
        3425405,
        927181,
        2016811,
        4393983,
        2157094,
        3202785,
        841015,
        2195513,
        2072370,
        2323280,
        2382196,
        3406262,
        838032,
        2424511,
        2222906,
        4100063,
        874429,
        2277115,
        3192205,
        810058,
        3959769,
        1938362,
        2139191,
        5024006,
        1020938,
        4310881,
        2167060,
        4203570,
        1475503,
        3194412,
        2572825,
        2306704,
        2286776,
        3305853,
        937500,
        4106289,
        1351358,
        2211584,
        2410775,
        2122749,
        4191388,
        972538,
        1949741,
        2116463,
        2346746,
        5423407,
        3051135,
        3339865,
        1006785,
        4108477,
        1547922,
        6038569,
        1330976,
        3741852,
        863901,
        2466139,
        3709745,
        863850,
        3496751,
        3771383,
        936253,
        3442305,
        884254,
        2306308,
        2062327,
        2370351,
        6312675,
        5054345,
        5861166,
        1765802,
        2288672,
        1942829,
        1899580,
        2692595
      ],
      "customStats": {},
      "counters": {},
      "concurrency": 1,
      "pendingRequests": 1,
      "scenariosAvoided": 0
    },
    {
      "timestamp": "2020-10-29T09:46:45.400Z",
      "scenariosCreated": 1000,
      "scenariosCompleted": 1000,
      "requestsCompleted": 1496,
      "latency": {
        "min": 0.6,
        "max": 42.8,
        "median": 2.2,
        "p95": 4.7,
        "p99": 11.9
      },
      "rps": {
        "count": 1496,
        "mean": 149.9
      },
      "scenarioDuration": {
        "min": 3.5,
        "max": 52,
        "median": 7,
        "p95": 11.9,
        "p99": 21.9
      },
      "scenarioCounts": {
        "Get Rides": 505,
        "Insert Rides": 495
      },
      "errors": {},
      "codes": {
        "200": 1496
      },
      "matches": 0,
      "latencies": [
        35907365,
        3034983,
        9214184,
        6128058,
        12398764,
        7046396,
        12620434,
        2115482,
        1038111,
        2066841,
        4210569,
        1211611,
        2523556,
        2069794,
        2168460,
        2288906,
        1967471,
        3215896,
        1162954,
        3423386,
        3966401,
        1507699,
        3012586,
        720680,
        3176714,
        1050807,
        3957400,
        851243,
        3043137,
        747022,
        3264295,
        1661037,
        2298632,
        2070561,
        1950862,
        3382551,
        949580,
        2198355,
        3921518,
        1378857,
        2127927,
        2642643,
        3432353,
        743603,
        2174864,
        2697375,
        2089978,
        2996848,
        2644639,
        3420450,
        775130,
        3089933,
        799545,
        2904210,
        2503059,
        2002599,
        3200857,
        815090,
        2429321,
        2110600,
        2510365,
        2291471,
        2079884,
        3728235,
        1509576,
        4595643,
        848889,
        1838248,
        3272625,
        1130126,
        3682500,
        837416,
        1880288,
        2016117,
        2255912,
        3519545,
        986167,
        2219181,
        4118860,
        1342414,
        2239044,
        2073099,
        1909668,
        4170829,
        998872,
        3176294,
        774896,
        2034780,
        2141082,
        2178590,
        3906688,
        1374710,
        4237749,
        1123681,
        2480788,
        2000513,
        2142529,
        2786625,
        2018234,
        3530679,
        1240207,
        2354162,
        2031660,
        1975078,
        2319489,
        2109147,
        3153294,
        2298830,
        4639806,
        1478511,
        2048856,
        3230037,
        791642,
        3159256,
        850927,
        3831962,
        2866756,
        2141748,
        2772817,
        2480600,
        3517327,
        774093,
        2095797,
        2052370,
        3920849,
        1250510,
        3493152,
        1786997,
        3848391,
        1018675,
        2038185,
        4681969,
        870520,
        4131726,
        1228743,
        3394245,
        3308359,
        809185,
        3087976,
        1366393,
        2514909,
        3240414,
        743578,
        3216730,
        848416,
        20110091,
        1775326,
        14278966,
        1036534,
        4498698,
        1325515,
        3977759,
        2209152,
        2317810,
        2065583,
        3370061,
        1194427,
        3931450,
        1007215,
        3529925,
        1024879,
        3725126,
        3582772,
        6795744,
        1552244,
        3389124,
        1434194,
        1885048,
        2189100,
        2043529,
        3600439,
        1014755,
        3907486,
        1051121,
        3534459,
        855696,
        3210626,
        817978,
        1993765,
        3873583,
        935835,
        2437951,
        4988995,
        1660094,
        3626731,
        1560816,
        3257763,
        724116,
        2022092,
        1911413,
        2250094,
        1977955,
        1930163,
        3114909,
        3304203,
        775152,
        1928553,
        4018717,
        1452089,
        3587624,
        860807,
        3190752,
        773099,
        2123024,
        4032906,
        1052149,
        3239018,
        852328,
        2114599,
        4632392,
        1528388,
        3970730,
        921502,
        3248131,
        838697,
        3041624,
        2428844,
        4333017,
        870856,
        3308224,
        886297,
        3660979,
        3605472,
        1994097,
        2529006,
        2555577,
        3223087,
        730979,
        2985372,
        754026,
        2335005,
        3270871,
        752342,
        3213324,
        730969,
        2073145,
        3420933,
        843799,
        10291508,
        4649558,
        7455750,
        9208887,
        3667449,
        3124161,
        753971,
        4436443,
        1474693,
        3814025,
        763851,
        1893517,
        3252579,
        1371807,
        3665189,
        942287,
        3052450,
        801202,
        1941003,
        1989642,
        3891656,
        918661,
        2379624,
        4639629,
        1303465,
        4040189,
        806418,
        3604521,
        737097,
        3085310,
        2295202,
        2307892,
        3270865,
        740837,
        1979933,
        3880859,
        2044594,
        3645046,
        761364,
        4144192,
        1508689,
        3471680,
        732882,
        3722131,
        1048535,
        3798884,
        920101,
        2323337,
        2004144,
        3424337,
        951501,
        2714683,
        3219157,
        810905,
        1949525,
        2155005,
        5101118,
        792345,
        3218326,
        762050,
        2145798,
        2527377,
        1955521,
        2069546,
        3449491,
        1080564,
        2039455,
        18940985,
        1415498,
        6496865,
        4948321,
        1088192,
        2300842,
        3360823,
        1419326,
        2608406,
        3873877,
        941982,
        3240055,
        785954,
        4949208,
        2317875,
        2211909,
        1959000,
        4150618,
        1112362,
        2485217,
        3259399,
        1562814,
        3424776,
        1070245,
        2474149,
        1925591,
        4056119,
        807839,
        5212844,
        1090706,
        3208183,
        667402,
        3457369,
        1089728,
        3675391,
        1346207,
        2003472,
        1914332,
        3320898,
        855783,
        3451512,
        852233,
        4264348,
        1182128,
        5067089,
        2423060,
        3423083,
        3236055,
        792764,
        1887990,
        2446706,
        3203287,
        714969,
        1898112,
        1903770,
        2304734,
        1969092,
        2008350,
        2528428,
        1892894,
        3353459,
        741786,
        3862521,
        1567676,
        2266700,
        3315139,
        791089,
        3366125,
        1268124,
        3825993,
        850399,
        5128740,
        1386740,
        4416262,
        5584995,
        2709239,
        1716165,
        1816974,
        2439448,
        2180390,
        1985187,
        3276299,
        1379782,
        3741229,
        822238,
        1931654,
        1838043,
        3342832,
        863727,
        1962532,
        3184120,
        4257934,
        2817547,
        3439148,
        887906,
        3605666,
        1007231,
        2013023,
        3428177,
        887128,
        3188486,
        1897352,
        1995042,
        3972628,
        874481,
        4616168,
        801648,
        3063529,
        923216,
        3596116,
        1324598,
        3981046,
        978081,
        1979148,
        2669670,
        3681898,
        953876,
        3423367,
        977916,
        4349073,
        827322,
        8669211,
        1850286,
        2350050,
        4251421,
        873847,
        2121866,
        1977099,
        4319469,
        3998016,
        1821615,
        2502738,
        3153095,
        835320,
        1958325,
        2016643,
        1963933,
        3017148,
        749534,
        3667688,
        857672,
        2081375,
        3133004,
        777587,
        2997520,
        1052268,
        2531070,
        1873070,
        3126590,
        4265420,
        930813,
        2313817,
        2158482,
        3681935,
        15727139,
        13390702,
        3146409,
        1252948,
        2476082,
        3192693,
        683991,
        2886595,
        730600,
        9713153,
        3633195,
        11779923,
        7069801,
        11939152,
        3613422,
        947854,
        3414557,
        750870,
        3794071,
        778527,
        1853833,
        2355068,
        1995944,
        3031529,
        815403,
        2172176,
        3370002,
        850152,
        3839900,
        876002,
        5724757,
        2137075,
        3721683,
        867601,
        3780031,
        1208262,
        2303480,
        3525911,
        1087009,
        1990529,
        3275905,
        799659,
        2752947,
        5003067,
        837447,
        3157121,
        795211,
        1898384,
        2342016,
        1960845,
        2089686,
        2287788,
        1924819,
        1975965,
        3688338,
        1182619,
        3552622,
        729203,
        2035593,
        2081328,
        4560993,
        1154596,
        2725455,
        3571082,
        1376854,
        3835322,
        828415,
        3200739,
        779160,
        1848246,
        3535140,
        2556549,
        2112129,
        2088834,
        5056303,
        918984,
        3424293,
        725743,
        4207109,
        771864,
        3514674,
        709034,
        3648839,
        964513,
        1959676,
        3049523,
        809573,
        2599823,
        3278404,
        825091,
        2110469,
        3717030,
        1106850,
        3688794,
        942675,
        3509074,
        823186,
        3397428,
        702217,
        2168571,
        2080821,
        2975523,
        985049,
        2171921,
        2164834,
        2076896,
        3167265,
        1327729,
        2452558,
        3016770,
        804712,
        6357810,
        1211464,
        3078713,
        765640,
        1997805,
        2783219,
        2244044,
        4231518,
        1162299,
        2365673,
        2707431,
        2150484,
        3089298,
        792631,
        1785255,
        3760781,
        834145,
        1993052,
        1904250,
        2216472,
        4750939,
        839034,
        2104820,
        3134657,
        1059635,
        2433216,
        2010565,
        1889403,
        2210301,
        2046999,
        1795526,
        2176955,
        3968659,
        1012697,
        2193233,
        2075192,
        3655394,
        762656,
        1910144,
        14632543,
        1894505,
        1920618,
        3301071,
        891274,
        2626364,
        3503467,
        991449,
        1994607,
        2892565,
        1283513,
        2281653,
        3054970,
        1068413,
        3245011,
        2408314,
        2054268,
        1794887,
        3999307,
        1171888,
        2012238,
        2206895,
        3694775,
        1206202,
        2232445,
        3067979,
        725461,
        3498075,
        930011,
        2368624,
        3143840,
        711059,
        1756817,
        2230426,
        3133612,
        2304944,
        4494362,
        834708,
        2267932,
        3442797,
        1076730,
        3119523,
        801678,
        1839517,
        3631097,
        753759,
        3177284,
        961854,
        2088377,
        5603056,
        1729747,
        1903572,
        3630570,
        964332,
        3348786,
        849656,
        3155657,
        3272088,
        1239050,
        3480684,
        860765,
        2160400,
        3223038,
        655125,
        1762787,
        3981967,
        1112340,
        3621401,
        3193730,
        695610,
        3120922,
        1342477,
        3855728,
        952631,
        1859193,
        3077668,
        734387,
        2251498,
        3254207,
        658604,
        1685579,
        2246417,
        1946057,
        2011167,
        3767266,
        959470,
        3243155,
        2368130,
        1922233,
        1844350,
        4866158,
        1044609,
        3453974,
        775568,
        2087571,
        6967125,
        4997228,
        6059662,
        3788557,
        1685133,
        3480970,
        795695,
        3197684,
        833761,
        3352882,
        756624,
        5432403,
        1727404,
        1943839,
        2959277,
        792896,
        2294418,
        2701322,
        3132763,
        984912,
        2709164,
        3105971,
        1982365,
        1836736,
        2092308,
        1954903,
        3056261,
        725705,
        4260366,
        1425723,
        2087570,
        3088095,
        1209898,
        3470646,
        1334116,
        2425305,
        1962171,
        1737624,
        3463621,
        1087396,
        2082352,
        1749218,
        2470189,
        3219754,
        1853611,
        2105535,
        2413076,
        2128614,
        2204385,
        1879201,
        19127366,
        12072985,
        895266,
        3415052,
        2120190,
        1980791,
        2205002,
        1926113,
        2025500,
        3445986,
        995327,
        1884768,
        1727497,
        3602175,
        899271,
        1806107,
        2831198,
        810027,
        2145521,
        3136657,
        764991,
        2054710,
        2179666,
        3294183,
        1022681,
        1923248,
        3304326,
        795253,
        3528764,
        919686,
        4711556,
        740921,
        2950402,
        1763232,
        4184015,
        1078372,
        3506443,
        1016383,
        1728870,
        3092393,
        806153,
        2053277,
        2151173,
        3351480,
        777375,
        2185404,
        2052591,
        3005458,
        642527,
        2700179,
        3500375,
        764165,
        2041102,
        4079297,
        935048,
        2268083,
        1842297,
        1704989,
        2243254,
        3580892,
        3010443,
        702633,
        3708955,
        1048894,
        3061774,
        803524,
        1812646,
        3793397,
        854129,
        3314886,
        729774,
        3036915,
        710099,
        1890303,
        2546146,
        1971001,
        3034820,
        743950,
        2272031,
        3207461,
        804755,
        1952359,
        3339011,
        1409889,
        3713413,
        1301972,
        1797518,
        1987593,
        2438840,
        2031332,
        2096730,
        2780077,
        4995909,
        721536,
        1829118,
        3234798,
        1099289,
        3844694,
        935785,
        1885142,
        3206848,
        878609,
        4497217,
        2229244,
        1972730,
        2439352,
        3926038,
        1428234,
        3463781,
        737924,
        5653591,
        1718440,
        5180620,
        1507283,
        6386514,
        1038298,
        4599221,
        2110451,
        2823804,
        3415205,
        810045,
        3374535,
        1023725,
        3494634,
        1270743,
        3248356,
        744619,
        1723741,
        3290356,
        2651701,
        3143486,
        743131,
        3634280,
        1091716,
        3574081,
        2055647,
        2412019,
        1939637,
        2912444,
        1026830,
        2792823,
        3363111,
        674789,
        1943415,
        3371184,
        1004216,
        2515536,
        1732925,
        4640807,
        756930,
        3425843,
        1077613,
        3102244,
        670489,
        15956280,
        4327433,
        1067706,
        4226153,
        802259,
        1689202,
        1766637,
        2324130,
        3030217,
        703320,
        1794647,
        2639340,
        1875449,
        2940561,
        763658,
        4021363,
        1058643,
        2303878,
        3463120,
        924222,
        2180307,
        3331263,
        803938,
        3552212,
        2658979,
        2247950,
        2524528,
        3189861,
        711020,
        2131687,
        2359286,
        3309543,
        1099695,
        2240400,
        2965388,
        3902650,
        845697,
        2935417,
        672543,
        2897342,
        730667,
        3719649,
        929094,
        3054206,
        594949,
        1601184,
        3812976,
        2080667,
        3678439,
        735739,
        2266440,
        9430170,
        4487176,
        7247161,
        3171149,
        4339196,
        740638,
        3428222,
        1135502,
        3158274,
        706056,
        2936097,
        673909,
        3534224,
        906733,
        1958068,
        2396112,
        2030837,
        2358224,
        1982852,
        3044227,
        746054,
        2312367,
        3431150,
        650585,
        2057819,
        3589709,
        1144491,
        1836333,
        3298181,
        1024965,
        2381061,
        3205727,
        737715,
        1705886,
        1728485,
        3843621,
        747554,
        3647526,
        3304917,
        722576,
        3475602,
        1174228,
        1914998,
        1823460,
        3131955,
        1109715,
        3422506,
        730308,
        2947362,
        622973,
        3053655,
        723149,
        2361637,
        3467634,
        743415,
        2998026,
        859989,
        2700652,
        2250460,
        2593820,
        4264049,
        975430,
        3319293,
        800704,
        4743987,
        1158758,
        2122067,
        3967044,
        2119594,
        2239850,
        3022291,
        729700,
        3649078,
        2385799,
        3627474,
        756546,
        3006472,
        744602,
        4157648,
        1008535,
        2245081,
        1919870,
        2996997,
        981893,
        2381539,
        3176419,
        724449,
        1613191,
        2033509,
        3151433,
        789718,
        3636875,
        1048864,
        2229840,
        3171288,
        738993,
        3390549,
        1164551,
        1807213,
        1925446,
        3506382,
        1058647,
        1989177,
        2620768,
        10249196,
        1825945,
        2922487,
        2324224,
        2142889,
        3143881,
        824449,
        3480347,
        951956,
        2456990,
        2240142,
        2212109,
        3365737,
        773890,
        1924682,
        3296685,
        1345117,
        2163968,
        1920149,
        3276476,
        715891,
        5433953,
        1378574,
        3083613,
        764582,
        2820770,
        685055,
        3471837,
        910971,
        3533480,
        1046940,
        1846147,
        3050963,
        1278830,
        2194276,
        3030169,
        775154,
        1786231,
        3604333,
        838950,
        1919659,
        1764697,
        2128037,
        4793957,
        734245,
        4018796,
        932156,
        2108896,
        1928775,
        3899518,
        1710215,
        1929070,
        1955232,
        3156833,
        752964,
        3579874,
        888153,
        3995054,
        1049953,
        3103912,
        1544233,
        1684864,
        2019155,
        3567144,
        811048,
        1790836,
        1713268,
        2244359,
        2982173,
        887286,
        2169319,
        3754515,
        1111307,
        2099542,
        3334730,
        1080280,
        11367041,
        2583488,
        7354106,
        4552823,
        2540637,
        5116123,
        2056422,
        4679033,
        1440299,
        2182613,
        2742537,
        2426738,
        3994874,
        2539119,
        2379460,
        4232996,
        2113302,
        2212306,
        4157229,
        945882,
        2375403,
        2185540,
        4151407,
        906216,
        2101871,
        3778714,
        1385610,
        2333004,
        2521799,
        1968792,
        3119185,
        737593,
        2021508,
        3473338,
        689617,
        1946079,
        1679710,
        1962788,
        1821323,
        3053959,
        661915,
        3788664,
        966292,
        3375182,
        800474,
        1782464,
        1776722,
        3467473,
        1062603,
        1865581,
        1762018,
        2016782,
        1920746,
        3481509,
        922963,
        2735769,
        2483277,
        1788601,
        1810786,
        1888653,
        3261907,
        829889,
        3444002,
        1048173,
        3920449,
        896803,
        3470075,
        952769,
        15891464,
        1440893,
        10332010,
        6240289,
        2696791,
        1093792,
        2869944,
        782685,
        2921491,
        708544,
        3642284,
        986150,
        3132810,
        656821,
        1788501,
        3404153,
        1092618,
        2996054,
        788690,
        3527658,
        708926,
        2044716,
        3756736,
        793627,
        1738377,
        1685145,
        2396732,
        3068372,
        657009,
        1692241,
        1819291,
        2339181,
        3853564,
        742153,
        2465206,
        3391442,
        745520,
        3079695,
        745740,
        3090720,
        647370,
        3542709,
        952009,
        1918183,
        1725919,
        3797349,
        1268694,
        3187275,
        756106,
        1826134,
        3925972,
        1065177,
        2220730,
        3071309,
        743773,
        4692989,
        696885,
        3833226,
        1378536,
        3194430,
        947316,
        2883987,
        685002,
        3488881,
        964233,
        2276921,
        1830474,
        3865966,
        4173702,
        983318,
        2875564,
        765546,
        1741673,
        3372264,
        783845,
        3192693,
        699566,
        1802345,
        3575443,
        1078081,
        3143459,
        785956,
        1939440,
        2095162,
        3130347,
        857734,
        2429898,
        3395491,
        927631,
        2152117,
        2033926,
        2178314,
        2644200,
        1985987,
        3102663,
        670565,
        3125023,
        1139411,
        3789477,
        829439,
        3033949,
        629260,
        2924081,
        3599443,
        2735094,
        1781195,
        1749405,
        3761590,
        1086084,
        3229051,
        2277745,
        4308261,
        1421649,
        2469064,
        1790616,
        4823151,
        660422,
        3384644,
        1149943,
        1969755,
        2166561,
        2271547,
        1993035,
        2735517,
        2143867,
        4144567,
        889155,
        1938098,
        1951220,
        3738064,
        986713,
        2072807,
        2968092,
        835842,
        3924935,
        1068672,
        1902026,
        1933798,
        4417217,
        1914798,
        3617076,
        879885,
        1732876,
        3131452,
        768758,
        3505047,
        759603,
        3062388,
        601108,
        2904554,
        688642,
        2035021,
        2045728,
        3189998,
        874326,
        3076458,
        42838580,
        3389198,
        10181722,
        9473096,
        2558102,
        10308261,
        9640563,
        4329728,
        6613724,
        1350638,
        2805951,
        675858,
        2949342,
        591364,
        3719065,
        745916,
        5455526,
        968122,
        2859122,
        796968,
        2958138,
        959130,
        3730901,
        1115885,
        1745544,
        2924023,
        649197,
        2962494,
        834543,
        1826910,
        2322709,
        5432431,
        1917757,
        2094980,
        1716386,
        1872090,
        2354606,
        1828996,
        2894500,
        804704,
        2245984,
        4651714,
        2152765,
        3726996,
        2937703,
        707409,
        2073120,
        3564758,
        1162683,
        4718808,
        2119376,
        2588741,
        2296040,
        3102854,
        808799,
        1628818,
        4636061,
        2666057,
        4525314,
        1748490,
        1795126,
        3614281,
        857014,
        2510605,
        4816132,
        2116109,
        1831733,
        3102237,
        1089942,
        3202109,
        845160,
        1717657,
        1619396,
        2027705,
        3376698,
        738509,
        8070217,
        2594886,
        5051831,
        3788994,
        4717264,
        1786751,
        1783528,
        3445493,
        743566,
        1792264,
        1748855,
        2089672,
        2872916,
        618027,
        1720211,
        3422614,
        1200070,
        1780940,
        2745687,
        596571,
        1968109,
        3427111,
        658153,
        1562375,
        3022653,
        797692,
        4265371,
        879260,
        1701200,
        3048395,
        1038142,
        2957586,
        998005,
        3075923,
        699488,
        3739344,
        910523,
        3942308,
        845421,
        3483546,
        754168,
        2809439,
        708056,
        1897637,
        3512630,
        1103933,
        2949325,
        682756,
        2787232,
        661533,
        3995496,
        1083451,
        3238647,
        676265,
        2951338,
        709637,
        1651093
      ],
      "customStats": {},
      "counters": {},
      "concurrency": 1,
      "pendingRequests": 1,
      "scenariosAvoided": 0
    },
    {
      "timestamp": "2020-10-29T09:46:55.400Z",
      "scenariosCreated": 1000,
      "scenariosCompleted": 1000,
      "requestsCompleted": 1481,
      "latency": {
        "min": 0.6,
        "max": 19.7,
        "median": 1.9,
        "p95": 4.3,
        "p99": 7.6
      },
      "rps": {
        "count": 1481,
        "mean": 148.25
      },
      "scenarioDuration": {
        "min": 3.5,
        "max": 33,
        "median": 6.5,
        "p95": 9.7,
        "p99": 17.4
      },
      "scenarioCounts": {
        "Get Rides": 519,
        "Insert Rides": 481
      },
      "errors": {},
      "codes": {
        "200": 1481
      },
      "matches": 0,
      "latencies": [
        19511572,
        2440658,
        2865392,
        3815962,
        2067176,
        1894328,
        1864391,
        1843655,
        2315429,
        2928370,
        2178461,
        2930856,
        725951,
        1639967,
        2267590,
        2936209,
        740552,
        2992336,
        887253,
        3572928,
        1188196,
        2938674,
        683311,
        1615815,
        1938606,
        1910702,
        2969363,
        709267,
        1760452,
        2404332,
        1686933,
        3087632,
        710183,
        3393324,
        1344531,
        2932500,
        694637,
        1816632,
        3318104,
        823729,
        2079254,
        1680549,
        2917461,
        696278,
        2415339,
        1761100,
        1698050,
        2278103,
        3060893,
        652362,
        1775739,
        1729941,
        3151242,
        789923,
        2921237,
        748997,
        3048936,
        663739,
        3642183,
        1106068,
        4567911,
        909905,
        2048804,
        3102383,
        699032,
        3166315,
        739152,
        2277785,
        5191460,
        984275,
        2256235,
        2859534,
        646171,
        1699427,
        3686271,
        937563,
        2895016,
        632439,
        8479882,
        6439741,
        5254259,
        3114634,
        679408,
        2066274,
        3409111,
        675021,
        3547514,
        818133,
        3654394,
        719189,
        2391053,
        2926401,
        1470145,
        3251185,
        714704,
        3220976,
        1150948,
        3021903,
        690174,
        1604712,
        1743207,
        1915603,
        1930118,
        4117647,
        1186226,
        2764219,
        3170655,
        660312,
        3000711,
        1226454,
        3726020,
        869387,
        2816810,
        1839837,
        1646812,
        6466080,
        876508,
        1574411,
        1624922,
        3688535,
        4731935,
        1903122,
        1703766,
        4288170,
        1022552,
        1849630,
        4299110,
        713322,
        4754371,
        896822,
        2269595,
        1686060,
        1578409,
        2106257,
        2850922,
        2408408,
        1674246,
        1844341,
        2781172,
        780385,
        1572218,
        1852851,
        2033217,
        1583687,
        2812642,
        845179,
        2312875,
        2988843,
        849703,
        2929229,
        628765,
        1748434,
        3033606,
        1038242,
        2204653,
        1750710,
        2074961,
        1655577,
        2068416,
        2003452,
        1713394,
        1842368,
        2185631,
        1893985,
        2878373,
        736082,
        1666364,
        3533804,
        3247894,
        886367,
        2926397,
        657131,
        4430414,
        1394516,
        1719572,
        3552928,
        994040,
        2068543,
        3286380,
        709071,
        3422997,
        617754,
        1731230,
        3303778,
        815310,
        1625774,
        3132982,
        618645,
        2033039,
        1994247,
        1821131,
        1798584,
        3044018,
        874772,
        2171383,
        1988174,
        3768750,
        724408,
        1821111,
        1702739,
        2677856,
        1661413,
        4783581,
        691243,
        1782502,
        2906050,
        733678,
        1587547,
        3412919,
        738211,
        3301668,
        800071,
        1626873,
        3213739,
        2545350,
        2876657,
        637629,
        2780025,
        681084,
        2027858,
        1887926,
        2833477,
        553152,
        2951635,
        1043312,
        4025627,
        1203026,
        1771945,
        2951173,
        604940,
        2160621,
        1697872,
        2959639,
        789173,
        1813597,
        3275995,
        664879,
        3114177,
        707496,
        2751976,
        981003,
        3213429,
        725136,
        2967630,
        749493,
        1685753,
        3868482,
        970316,
        3183802,
        752491,
        2042903,
        3463484,
        1175372,
        1997716,
        2452506,
        3458166,
        847410,
        5177782,
        707213,
        1581699,
        1669815,
        4808959,
        1123757,
        1656024,
        1947452,
        2006172,
        2974318,
        754588,
        3241168,
        629819,
        1947817,
        1825810,
        2968462,
        792459,
        1761471,
        3613008,
        820509,
        2853359,
        610287,
        2767524,
        613483,
        1718389,
        3010153,
        743194,
        3253613,
        756568,
        1984263,
        3465059,
        801649,
        2892009,
        665273,
        3085873,
        665231,
        3969028,
        1563259,
        1703098,
        2958461,
        652243,
        2216256,
        3125936,
        694909,
        2884943,
        616196,
        3131875,
        1228884,
        3602188,
        965641,
        1933127,
        3048282,
        740120,
        2162780,
        4517939,
        828811,
        2900703,
        816220,
        1732251,
        2811577,
        592381,
        1618487,
        1869979,
        1949527,
        1674543,
        3060422,
        1097473,
        2385667,
        3041761,
        675833,
        2951171,
        725351,
        1741161,
        1960185,
        2080235,
        3452898,
        841184,
        3310144,
        747848,
        2728283,
        666015,
        2951242,
        657198,
        3736971,
        1067482,
        1788979,
        1703032,
        3545857,
        946940,
        3043373,
        636786,
        1775894,
        1697742,
        2127896,
        3146230,
        690787,
        3037323,
        670689,
        3911790,
        1238139,
        2838210,
        670876,
        1796837,
        3408077,
        917658,
        2047139,
        3057087,
        644098,
        3200626,
        958669,
        2191273,
        4576297,
        709646,
        3032392,
        799410,
        2006747,
        1748892,
        3175085,
        745727,
        3670018,
        1104568,
        1838581,
        3246551,
        650213,
        1935046,
        1970473,
        1776648,
        1651590,
        2393388,
        1640728,
        1765726,
        3303292,
        1224194,
        2991859,
        781712,
        2871616,
        657330,
        3237879,
        902260,
        3332849,
        744069,
        1613093,
        3078170,
        693056,
        3697259,
        871007,
        2831329,
        751952,
        2848012,
        637184,
        2193012,
        1883557,
        1831092,
        7834350,
        3613677,
        3347183,
        926488,
        3697952,
        889496,
        4340894,
        2562503,
        2650066,
        5476359,
        1342818,
        2326220,
        4591386,
        974665,
        1935360,
        3668174,
        811374,
        2770763,
        720876,
        7391006,
        5413059,
        13142667,
        3740410,
        762133,
        2989488,
        662875,
        3227746,
        1091648,
        1751321,
        1556555,
        1769335,
        3263005,
        671759,
        1651621,
        2397395,
        5355633,
        1678660,
        3150604,
        824561,
        1972847,
        2149938,
        2521771,
        4392365,
        703315,
        1724648,
        3222642,
        754197,
        2872815,
        653498,
        2368375,
        2543070,
        1837132,
        2429005,
        3418020,
        611813,
        2943292,
        2692017,
        2926648,
        1097886,
        3577114,
        963409,
        2922722,
        662401,
        4319654,
        1099493,
        2536586,
        2753886,
        1915681,
        2123571,
        3439224,
        678292,
        1895855,
        1608731,
        3087155,
        899389,
        8012314,
        2773991,
        7270178,
        2648613,
        5036832,
        2752032,
        2152110,
        3628108,
        917330,
        2703115,
        608353,
        3932299,
        741143,
        1844214,
        2030811,
        1960791,
        2983730,
        672963,
        2254572,
        2898013,
        613029,
        1772564,
        3054176,
        725808,
        1868299,
        2305293,
        2925064,
        1048105,
        3428161,
        824237,
        2915542,
        637118,
        2984525,
        783520,
        3815055,
        956268,
        2908446,
        630905,
        1668137,
        3450124,
        770468,
        3072974,
        761416,
        1759162,
        1556341,
        2214900,
        3047235,
        671080,
        1642106,
        1864812,
        2817979,
        632530,
        1791595,
        1932740,
        1970255,
        1693009,
        1621378,
        2050636,
        1759176,
        1642532,
        1764261,
        3269996,
        974935,
        2507287,
        2111715,
        1956625,
        4672220,
        655004,
        2017232,
        3295543,
        706393,
        1607509,
        2859216,
        785397,
        2576509,
        1653273,
        4408653,
        984832,
        2070607,
        5167047,
        709069,
        2846633,
        698831,
        1718371,
        3054135,
        1420536,
        3088466,
        660946,
        2929066,
        649170,
        3908403,
        921091,
        1811643,
        1643790,
        2361637,
        3258038,
        710654,
        2843422,
        618701,
        2822926,
        1190552,
        3522620,
        882585,
        2740031,
        684363,
        2817413,
        668145,
        2086989,
        1747066,
        2866436,
        737653,
        3660177,
        1244201,
        3405072,
        628052,
        2868489,
        647362,
        1648371,
        3032433,
        859477,
        1738710,
        3587620,
        1252917,
        2334110,
        2965899,
        669452,
        1715227,
        2233720,
        2817545,
        653426,
        1611346,
        3443724,
        709995,
        4570167,
        633125,
        1625298,
        1733870,
        2220261,
        2843470,
        774321,
        2145738,
        2013649,
        2820414,
        664099,
        2830783,
        661299,
        3018832,
        1262719,
        3378442,
        960052,
        1615384,
        1813377,
        3253526,
        732913,
        1812784,
        4287463,
        918312,
        4295597,
        1064535,
        3325883,
        619508,
        1769977,
        1635356,
        3402287,
        789589,
        1549615,
        3019849,
        626257,
        1940808,
        3193634,
        592275,
        1794587,
        5088679,
        1544908,
        2442927,
        1682530,
        3469924,
        857622,
        2961148,
        1017698,
        1702833,
        3179728,
        1249510,
        3685585,
        912542,
        1615298,
        2667805,
        623590,
        1757866,
        2725475,
        2192528,
        1651160,
        3015308,
        1200600,
        2617933,
        1872817,
        1883081,
        4530628,
        1360159,
        2806982,
        695505,
        3068825,
        777920,
        1822949,
        2014578,
        3847545,
        847326,
        6663679,
        3223754,
        4816063,
        899948,
        1809630,
        3271030,
        842569,
        2197073,
        1831606,
        1613027,
        2417044,
        3191304,
        711858,
        2882525,
        695068,
        5187110,
        1911514,
        3125644,
        659079,
        1753237,
        2179317,
        3038642,
        770090,
        1909537,
        3802334,
        1221269,
        1940010,
        1675147,
        2082202,
        3148254,
        701616,
        1554131,
        3127941,
        845369,
        1947574,
        1942388,
        1962900,
        1881939,
        2903323,
        672194,
        2876176,
        703483,
        3268366,
        894266,
        1899409,
        2992847,
        597953,
        1673990,
        5784257,
        2075333,
        4624068,
        718656,
        1759880,
        2246980,
        2948871,
        761061,
        2947490,
        654718,
        3016692,
        916580,
        2005571,
        2877348,
        713798,
        1636423,
        2003548,
        1747117,
        4465993,
        1041859,
        3133273,
        2907916,
        629284,
        1742167,
        1626303,
        3413113,
        697878,
        2925958,
        688488,
        2958265,
        701346,
        1854184,
        3079465,
        636388,
        1753501,
        3899081,
        1397053,
        2094388,
        1631086,
        2922608,
        765355,
        1864638,
        1849531,
        2946845,
        1356413,
        5475758,
        1868944,
        2847717,
        733068,
        3044877,
        802583,
        3814639,
        1012269,
        2965146,
        739846,
        1560663,
        5392330,
        918108,
        1989259,
        1746280,
        2924200,
        839294,
        3905192,
        1144677,
        2839381,
        705781,
        3005314,
        621002,
        3434143,
        1062965,
        2806166,
        1157826,
        1756315,
        1646562,
        3073952,
        706471,
        1680584,
        1704366,
        3109355,
        722792,
        3132568,
        817114,
        1990287,
        1846870,
        1847234,
        1712421,
        4884650,
        1433951,
        3561635,
        940404,
        1620037,
        2965130,
        655121,
        2279107,
        3050845,
        659334,
        2996230,
        731976,
        3448949,
        1138424,
        1839797,
        2870052,
        587052,
        1832790,
        3058628,
        677158,
        1719867,
        2933083,
        742961,
        3767019,
        1012138,
        1683900,
        4632475,
        768483,
        4262395,
        1252903,
        1718835,
        1723125,
        3983632,
        2108704,
        1713083,
        3295648,
        751240,
        6211574,
        3001368,
        990210,
        2410666,
        2069987,
        2977319,
        798549,
        3687123,
        1018703,
        2933825,
        792638,
        1709330,
        3148297,
        904259,
        2068564,
        3622442,
        933999,
        1666065,
        2895477,
        607462,
        2082456,
        1893841,
        1717083,
        1605158,
        2213752,
        2896794,
        736931,
        1822277,
        2117133,
        2823621,
        683524,
        2928111,
        704666,
        1763361,
        1609427,
        1592243,
        1729980,
        3155562,
        716978,
        1564527,
        1645691,
        2003843,
        3230498,
        1069453,
        1887210,
        2315950,
        1711275,
        1565638,
        3225475,
        1067936,
        3194452,
        712085,
        2984998,
        647568,
        1788874,
        2339890,
        1726147,
        9936621,
        8479489,
        11522862,
        19736546,
        2967512,
        10524468,
        2527871,
        719704,
        3583166,
        735036,
        2872549,
        665965,
        2770251,
        734106,
        1919001,
        1691318,
        3037643,
        762941,
        2570341,
        3129250,
        780416,
        1759165,
        2867007,
        1165010,
        3449453,
        768996,
        2841609,
        678915,
        1620333,
        3975476,
        1083016,
        2888025,
        642699,
        1671899,
        3620833,
        1282340,
        3104207,
        736395,
        3084092,
        701208,
        1912161,
        1805322,
        2156311,
        2868819,
        1115427,
        3794226,
        952659,
        2816033,
        637992,
        1643219,
        3331853,
        1187973,
        3056603,
        581923,
        2734338,
        635527,
        1651552,
        3115568,
        689250,
        1514653,
        1697763,
        4371542,
        2190748,
        2061258,
        3418893,
        1182052,
        2959163,
        715137,
        1617353,
        2002991,
        2093895,
        1599795,
        1573254,
        3064580,
        721204,
        1889778,
        2325477,
        2338855,
        2225767,
        1908233,
        7130628,
        1056287,
        2005671,
        2829804,
        695964,
        1668345,
        4519620,
        1134927,
        2970951,
        616057,
        3083188,
        884922,
        2219499,
        3136843,
        645135,
        2995880,
        650068,
        3486064,
        792940,
        3402074,
        684911,
        2816077,
        628620,
        1696781,
        2262407,
        2733202,
        738560,
        1592907,
        1926624,
        1624950,
        1535146,
        1540943,
        3127914,
        2804597,
        629538,
        1593595,
        2446208,
        1575045,
        3038376,
        814360,
        2151172,
        1896325,
        1673433,
        2889795,
        750152,
        1804662,
        5135820,
        1101116,
        2087836,
        2010793,
        1674247,
        4682614,
        870792,
        4319026,
        1503127,
        2183448,
        1679068,
        1621162,
        1842459,
        1620321,
        2875058,
        652888,
        3687719,
        1049765,
        3095833,
        676703,
        2900365,
        650586,
        4209483,
        795504,
        3761863,
        689575,
        1800908,
        1749954,
        2272901,
        1645906,
        1744288,
        2601581,
        1656931,
        4764804,
        1757551,
        2915103,
        3912345,
        827932,
        3177337,
        870992,
        3226158,
        758679,
        1897574,
        3842678,
        1034291,
        1947376,
        3938322,
        877529,
        3506180,
        752341,
        3147197,
        773836,
        2279048,
        4134742,
        760249,
        3129406,
        789046,
        3011086,
        1241152,
        2089014,
        1628156,
        1585185,
        4000923,
        904129,
        2898699,
        1607936,
        3680933,
        1139958,
        1899076,
        2899897,
        667478,
        1622197,
        2195144,
        1868315,
        3094208,
        642429,
        3890000,
        1170383,
        1733209,
        3004020,
        2468755,
        1992189,
        1912464,
        2744599,
        3389317,
        847912,
        4398353,
        825152,
        3891680,
        769817,
        2957218,
        840681,
        3104915,
        763164,
        1789455,
        2923793,
        736125,
        4022330,
        1246015,
        2946749,
        617620,
        5283563,
        754784,
        3098590,
        879977,
        3423917,
        717791,
        1718172,
        1751106,
        3239390,
        3677683,
        779425,
        1830703,
        2023239,
        1906012,
        1691726,
        1651988,
        2052638,
        1638190,
        3044729,
        2114892,
        3556515,
        1052162,
        4322192,
        789118,
        1636391,
        3470458,
        862622,
        1927972,
        2916071,
        1205486,
        1746391,
        2986718,
        786682,
        3247726,
        1048095,
        1889009,
        2031853,
        2831236,
        602553,
        3014601,
        590553,
        3599643,
        972836,
        3355243,
        660655,
        1852258,
        3649324,
        1139406,
        1871818,
        1619660,
        1541302,
        3752035,
        718637,
        1577280,
        2657408,
        902834,
        4091842,
        1369352,
        1578181,
        1117676,
        1796230,
        1928327,
        2866982,
        640879,
        2780302,
        645696,
        2213582,
        2859016,
        637166,
        1859526,
        3181169,
        1090164,
        3097210,
        818974,
        3201434,
        653205,
        1850986,
        3133545,
        867890,
        4214350,
        626686,
        2871795,
        661934,
        1757557,
        1784898,
        2243821,
        2661769,
        3332188,
        686530,
        2969521,
        618904,
        1663173,
        2306034,
        1639354,
        3064422,
        784586,
        2080404,
        2004299,
        1831778,
        3280528,
        1149627,
        3095423,
        609807,
        1758789,
        3554527,
        762810,
        1847517,
        2739207,
        667595,
        1531503,
        3735805,
        951499,
        2786218,
        628843,
        2847318,
        672430,
        3419768,
        1176640,
        1657544,
        2861079,
        603815,
        3019255,
        726957,
        3098363,
        766595,
        1881675,
        3165341,
        894993,
        3979133,
        1149497,
        2918993,
        674592,
        1805492,
        2111982,
        1920005,
        1739408,
        1671799,
        3397187,
        1773221,
        2930723,
        646677,
        1961368,
        1719323,
        4398521,
        714107,
        1988129,
        3218705,
        676135,
        1720254,
        2964569,
        1060332,
        2160145,
        1699435,
        3145106,
        854008,
        4577017,
        2977393,
        685300,
        5171210,
        1882606,
        4978122,
        888959,
        1797223,
        1871604,
        2483748,
        1947568,
        1709080,
        1732384,
        3720026,
        1037679,
        3155164,
        927813,
        2080400,
        3620658,
        1033347,
        3233495,
        735785,
        3003680,
        687749,
        3228177,
        1001250,
        1891777,
        2785767,
        624893,
        3440958,
        742445,
        3985052,
        1103697,
        2902799,
        700983,
        1748244,
        3570623,
        1245616,
        3187539,
        670946,
        2819771,
        630602,
        1588972,
        2077493,
        4347224,
        585412,
        1717826,
        3842816,
        1036021,
        2794573,
        550894,
        2782581,
        902305,
        8713108,
        4110540,
        7666575,
        8950528,
        3923195,
        6589310,
        2705209,
        1734208,
        3010515,
        671347,
        2162965,
        2956795,
        654211,
        2771658,
        733124,
        1773003,
        2897497,
        781022,
        2843801,
        777716,
        2336956,
        3257100,
        623578,
        1645610,
        1626829,
        2333775,
        2799613,
        695209,
        2898434,
        829535,
        3742939,
        972633,
        2834240,
        731078,
        1594957,
        1710335,
        1862427,
        1614563,
        2829248,
        640604,
        2246516,
        1623734,
        1923792,
        2343337,
        3312813,
        627278,
        1701690,
        2978142,
        1062896,
        3145552,
        3288565,
        9059435,
        5344434,
        9219173,
        2004088,
        1956053,
        1992292,
        3755162,
        732098,
        1923109,
        1692552,
        1782380,
        3790289,
        738752,
        2921607,
        741392,
        2355527,
        3479264,
        949944,
        1576901,
        3505101,
        841971,
        1920391,
        2898153,
        627665,
        1546002,
        2265605,
        1790307,
        2828937,
        652362,
        3603893,
        906333,
        3033560,
        743510,
        2990882,
        593056,
        2475515,
        3237619,
        709684,
        2792959,
        682343,
        2912052,
        643095,
        3058905,
        824085,
        3770132,
        784775,
        1934927,
        2499031,
        2611088,
        3985879,
        757111,
        6315655,
        1384653,
        2429532,
        2761784,
        612925,
        4040371,
        800566,
        1811438,
        2179788,
        1692761,
        3348796,
        4144980,
        764937,
        4128512,
        663168,
        1569091,
        3458698,
        721968,
        4641092,
        2386548,
        4271456,
        706702,
        3173972,
        1058831
      ],
      "customStats": {},
      "counters": {},
      "concurrency": 1,
      "pendingRequests": 1,
      "scenariosAvoided": 0
    },
    {
      "timestamp": "2020-10-29T09:46:55.908Z",
      "scenariosCreated": 1,
      "scenariosCompleted": 2,
      "requestsCompleted": 3,
      "latency": {
        "min": 0.8,
        "max": 29.4,
        "median": 15.7,
        "p95": 29.4,
        "p99": 29.4
      },
      "rps": {
        "count": 2,
        "mean": 4
      },
      "scenarioDuration": {
        "min": 17.8,
        "max": 37.3,
        "median": 27.6,
        "p95": 37.3,
        "p99": 37.3
      },
      "scenarioCounts": {
        "Insert Rides": 1
      },
      "errors": {},
      "codes": {
        "200": 3
      },
      "matches": 0,
      "latencies": [
        15655361,
        29417678,
        808833
      ],
      "customStats": {},
      "counters": {},
      "concurrency": 0,
      "pendingRequests": 0,
      "scenariosAvoided": 0
    }
  ]
}